setup.cfg
setup.py
scrapyc/__init__.py
scrapyc/cli.py
scrapyc/client.py
scrapyc/exceptions.py
scrapyc.egg-info/PKG-INFO
scrapyc.egg-info/SOURCES.txt
scrapyc.egg-info/dependency_links.txt
scrapyc.egg-info/entry_points.txt
scrapyc.egg-info/not-zip-safe
scrapyc.egg-info/requires.txt
scrapyc.egg-info/top_level.txt
tests/__init__.py
tests/test_cli.py
tests/test_http.py
tests/test_import.py
tests/test_read.py
tests/test_schedule.py