Metadata-Version: 1.0
Name: scrapyc
Version: 0.0.4
Summary: Simple client to scrapyd. Done right.
Home-page: https://github.com/f213/scrapyd-client/
Author: Fedor Borshev
Author-email: f@f213.in
License: MIT
Platform: UNKNOWN
